{
  "title": "Анализ и оптимизация производительности приложений — Мониторинг в реальном времени",
  "description": "Фрагмент из «Анализ и оптимизация производительности приложений»: Мониторинг в реальном времени.",
  "tags": [
    "dev-debug",
    "encyclopedia",
    "112"
  ],
  "order": 10,
  "series": "code-414-112",
  "seriesOrder": 10,
  "seriesTitle": "Анализ и оптимизация производительности приложений",
  "encyclopediaUrl": "https://spirzen.ru/encyclopedia/4-code-dev/4-14-razrabotka-i-otladka/112"
}
